README.rst
setup.py
hpoliced/__init__.py
hpoliced/cli.py
hpoliced.egg-info/PKG-INFO
hpoliced.egg-info/SOURCES.txt
hpoliced.egg-info/dependency_links.txt
hpoliced.egg-info/entry_points.txt
hpoliced.egg-info/requires.txt
hpoliced.egg-info/top_level.txt