Metadata-Version: 1.1
Name: hpoliced
Version: 0.0.4
Summary: Turns HTTPolice into a web server
Home-page: https://github.com/activesphere/httpolice-devtool/hpoliced
Author: ActiveSphere
Author-email: shinde.rohitt@gmail.com
License: MIT
Keywords: httpolice,http,lint,linting,tool
Platform: UNKNOWN
Classifier: Programming Language :: Python
Classifier: Intended Audience :: Developers
Classifier: Intended Audience :: Developers
Classifier: Development Status :: 4 - Beta
Classifier: Environment :: Console
Classifier: License :: OSI Approved :: MIT License
Classifier: Topic :: Internet :: WWW/HTTP
Classifier: Topic :: Internet :: WWW/HTTP :: WSGI :: Application
Classifier: Topic :: Software Development :: Quality Assurance
